cranes/__init__.py
cranes/analysis_and_visualization.py
cranes/base.py
cranes/community_damage_sampling.py
cranes/downtime_logistics.py
cranes/impeding_factor_assigments.py
cranes/impeding_factor_parameter_dictionary.json
cranes/impeding_factor_parameter_identification.py
cranes/mapping.py
cranes-1.0.0.dist-info/LICENSE
cranes-1.0.0.dist-info/METADATA
cranes-1.0.0.dist-info/WHEEL
cranes-1.0.0.dist-info/top_level.txt
cranes-1.0.0.dist-info/RECORD
