Metadata-Version: 2.1
Name: cranes
Version: 1.0.0
Summary: Cordons in Recovery Assessments of Neighborhoods following Earthquake Simulations
Home-page: https://github.com/annehulsey/cranes
Author: Anne Hulsey
Author-email: anne.hulsey@auckland.ac.nz
License: MIT License
Platform: any
Classifier: Programming Language :: Python
Classifier: Natural Language :: English
Classifier: Intended Audience :: Education
Classifier: Intended Audience :: Science/Research
Classifier: License :: OSI Approved :: MIT License
Classifier: Topic :: Scientific/Engineering
License-File: LICENSE
Requires-Dist: numpy
Requires-Dist: pandas
Requires-Dist: geopandas
Requires-Dist: h5py
Requires-Dist: utm
Requires-Dist: matplotlib
Requires-Dist: geojson
Requires-Dist: shapely
